pythaisa/__init__.py
tests/__init__.py
pythaisa-0.2.1.dist-info/LICENSE
pythaisa-0.2.1.dist-info/METADATA
pythaisa-0.2.1.dist-info/WHEEL
pythaisa-0.2.1.dist-info/top_level.txt
pythaisa-0.2.1.dist-info/RECORD
