Metadata-Version: 2.1
Name: pythaisa
Version: 0.2.1
Summary: Python Thai Sentiment Analysis
Home-page: https://github.com/PyThaiNLP/thai_sentiment_analysis
Author: wannaphong
Author-email: wannaphong@kkumail.com
License: Apache Software License 2.0
Keywords: NLP,natural language processing,text analytics,ThaiNLP,text processing,localization
Platform: UNKNOWN
Classifier: Programming Language :: Python :: 3
Classifier: Intended Audience :: Developers
Classifier: License :: OSI Approved :: Apache Software License
Classifier: Natural Language :: Thai
Classifier: Topic :: Scientific/Engineering :: Artificial Intelligence
Classifier: Topic :: Text Processing
Classifier: Topic :: Text Processing :: General
Classifier: Topic :: Text Processing :: Linguistic
Requires-Python: >=3.6
Requires-Dist: pythainlp
Requires-Dist: nltk
